[
    {
        "ADDRESS": "Samaj Mandir', Opp. New English School, Vasai (W), Dist. Thane 401 201 Tel : 0250 - 2322617, 2326984, 2326998",
        "BANK": "Vasai Vikas Sahakari Bank",
        "BANKCODE": "VVSB",
        "BRANCH": "Vasai Vikas Sahakari Bank IMPS",
        "CENTRE": "VASAI",
        "CITY": "VASAI",
        "CONTACT": "2326984",
        "DISTRICT": "THANE",
        "IFSC": "VVSB0000001",
        "IMPS": true,
        "MICR": "NA",
        "NEFT": true,
        "RTGS": true,
        "STATE": "MAHARASHTRA",
        "SWIFT": "",
        "UPI": true
    },
    {
        "ADDRESS": "Samaj Mandir', Opp. New English School, Vasai (W), Dist. Thane 401 201 Tel : 0250 - 2322617, 2326984, 2326998",
        "BANK": "Vasai Vikas Sahakari Bank",
        "BANKCODE": "VVSB",
        "BRANCH": "VASAI",
        "CENTRE": "PAPADI",
        "CITY": "PAPADI",
        "CONTACT": "2322617",
        "DISTRICT": "THANE",
        "IFSC": "VVSB0000002",
        "IMPS": true,
        "MICR": "400803002",
        "NEFT": true,
        "RTGS": true,
        "STATE": "MAHARASHTRA",
        "SWIFT": "",
        "UPI": true
    },
    {
        "ADDRESS": "Thakur Arcade, Near Railway Station, Virar (W), Dist Thane - 401 303 Tel : 0250 - 2502733, 2502536",
        "BANK": "Vasai Vikas Sahakari Bank",
        "BANKCODE": "VVSB",
        "BRANCH": "VIRAR",
        "CENTRE": "VIRAR",
        "CITY": "VIRAR",
        "CONTACT": "2502733",
        "DISTRICT": "THANE",
        "IFSC": "VVSB0000003",
        "IMPS": true,
        "MICR": "400803003",
        "NEFT": true,
        "RTGS": true,
        "STATE": "MAHARASHTRA",
        "SWIFT": "",
        "UPI": true
    },
    {
        "ADDRESS": "Adinath Apt., Ambadi Road, Navghar, Vasai (W), Dist. Thane - 401 201 Tel : 0250 - 2334398, 2348946",
        "BANK": "Vasai Vikas Sahakari Bank",
        "BANKCODE": "VVSB",
        "BRANCH": "NAVGHAR",
        "CENTRE": "VASAI",
        "CITY": "VASAI",
        "CONTACT": "2334398",
        "DISTRICT": "THANE",
        "IFSC": "VVSB0000004",
        "IMPS": true,
        "MICR": "400803004",
        "NEFT": true,
        "RTGS": true,
        "STATE": "MAHARASHTRA",
        "SWIFT": "",
        "UPI": true
    },
    {
        "ADDRESS": "Mudra Shopping Complex, Kacheri Road, Palghar (W), Dist. Thane - 401 404, Tel : 02525 - 251409,251410",
        "BANK": "Vasai Vikas Sahakari Bank",
        "BANKCODE": "VVSB",
        "BRANCH": "PALGHAR",
        "CENTRE": "PALGHAR",
        "CITY": "PALGHAR",
        "CONTACT": "251409",
        "DISTRICT": "THANE",
        "IFSC": "VVSB0000005",
        "IMPS": true,
        "MICR": "400803005",
        "NEFT": true,
        "RTGS": true,
        "STATE": "MAHARASHTRA",
        "SWIFT": "",
        "UPI": true
    },
    {
        "ADDRESS": "Shree Apartment, Near Railway Station, Nallasopara (W), Dist. Thane - 401 203, Tel : 0250 - 2403582",
        "BANK": "Vasai Vikas Sahakari Bank",
        "BANKCODE": "VVSB",
        "BRANCH": "SAPHALE",
        "CENTRE": "SAPHALA",
        "CITY": "SAPHALA",
        "CONTACT": "2403582",
        "DISTRICT": "THANE",
        "IFSC": "VVSB0000006",
        "IMPS": true,
        "MICR": "400803006",
        "NEFT": true,
        "RTGS": true,
        "STATE": "MAHARASHTRA",
        "SWIFT": "",
        "UPI": true
    },
    {
        "ADDRESS": "Devbhoomi Commercial Complex, Near Saphale Station, Saphale (E), Dist. Thane - 401 102, Tel : 952525 - 230539",
        "BANK": "Vasai Vikas Sahakari Bank",
        "BANKCODE": "VVSB",
        "BRANCH": "NALASOPARA",
        "CENTRE": "NALLASOPARA",
        "CITY": "NALLASOPARA",
        "CONTACT": "230539",
        "DISTRICT": "THANE",
        "IFSC": "VVSB0000007",
        "IMPS": true,
        "MICR": "400803007",
        "NEFT": true,
        "RTGS": true,
        "STATE": "MAHARASHTRA",
        "SWIFT": "",
        "UPI": true
    },
    {
        "ADDRESS": "New Krishna Niwas, Chandavarkar Cross Road, Borivali (W), Mumbai 400 092, Tel : 022 - 28956608 / 09 /10",
        "BANK": "Vasai Vikas Sahakari Bank",
        "BANKCODE": "VVSB",
        "BRANCH": "BORIVALI",
        "CENTRE": "MUMBAI",
        "CITY": "MUMBAI",
        "CONTACT": "28956608",
        "DISTRICT": "GREATER BOMBAY",
        "IFSC": "VVSB0000008",
        "IMPS": true,
        "MICR": "400803008",
        "NEFT": true,
        "RTGS": true,
        "STATE": "MAHARASHTRA",
        "SWIFT": "",
        "UPI": true
    },
    {
        "ADDRESS": "Vardhaman Industrial Complex premises co op. Soc. Ltd., Unit No. 3,Gokul Nagar, Opp. Jarimari Mata Mandir, Near Navnit Motors, L.B.S. Marg, Thane (W) - 400 601. Tel.:022-21721013/14",
        "BANK": "Vasai Vikas Sahakari Bank",
        "BANKCODE": "VVSB",
        "BRANCH": "THANE",
        "CENTRE": "THANE",
        "CITY": "THANE",
        "CONTACT": "21721013",
        "DISTRICT": "THANE",
        "IFSC": "VVSB0000009",
        "IMPS": true,
        "MICR": "400803009",
        "NEFT": true,
        "RTGS": true,
        "STATE": "MAHARASHTRA",
        "SWIFT": "",
        "UPI": true
    },
    {
        "ADDRESS": "Ground Floor, Gala No. 10,11,12, Sidhi Vinayak Arcade, Near Makwana Complex, V. S. Marg, Virar (E), Dist. Thane",
        "BANK": "Vasai Vikas Sahakari Bank",
        "BANKCODE": "VVSB",
        "BRANCH": "NARINGI",
        "CENTRE": "VIRAR",
        "CITY": "VIRAR",
        "CONTACT": "6099919",
        "DISTRICT": "THANE",
        "IFSC": "VVSB0000010",
        "IMPS": true,
        "MICR": "400803010",
        "NEFT": true,
        "RTGS": true,
        "STATE": "MAHARASHTRA",
        "SWIFT": "",
        "UPI": true
    },
    {
        "ADDRESS": "Shop No. H/11, 1st Floor, Kingston Tower, Above Dominos Pizza,  Opposite Viva College, Virar (West), Dist. Thane",
        "BANK": "Vasai Vikas Sahakari Bank",
        "BANKCODE": "VVSB",
        "BRANCH": "BOLINJ",
        "CENTRE": "BOLINJ",
        "CITY": "BOLINJ",
        "CONTACT": "6512777",
        "DISTRICT": "THANE",
        "IFSC": "VVSB0000011",
        "IMPS": true,
        "MICR": "400803011",
        "NEFT": true,
        "RTGS": true,
        "STATE": "MAHARASHTRA",
        "SWIFT": "",
        "UPI": true
    },
    {
        "ADDRESS": "Govind Shantinagar C.H.S, Flat No.1 & Shop No.12/13/14, Sector 5, Near Jain Mandir, Bldg. No. B-31, Ground Floor, Mira Road, Dist Thane.",
        "BANK": "Vasai Vikas Sahakari Bank",
        "BANKCODE": "VVSB",
        "BRANCH": "MIRA ROAD",
        "CENTRE": "MIRA-BHAYANDAR",
        "CITY": "MIRA-BHAYANDAR",
        "CONTACT": "28112347",
        "DISTRICT": "THANE",
        "IFSC": "VVSB0000012",
        "IMPS": true,
        "MICR": "400803012",
        "NEFT": true,
        "RTGS": true,
        "STATE": "MAHARASHTRA",
        "SWIFT": "",
        "UPI": true
    },
    {
        "ADDRESS": "Yash Siddhi Residency; Boisar Palghar Road; beside Hotel Sun Rose; Boisar (West) Maharashtra,",
        "BANK": "Vasai Vikas Sahakari Bank",
        "BANKCODE": "VVSB",
        "BRANCH": "BOISAR",
        "CENTRE": "BOISAR",
        "CITY": "BOISAR",
        "CONTACT": "274666",
        "DISTRICT": "THANE",
        "IFSC": "VVSB0000013",
        "IMPS": true,
        "MICR": "401802001",
        "NEFT": true,
        "RTGS": true,
        "STATE": "MAHARASHTRA",
        "SWIFT": "",
        "UPI": true
    },
    {
        "ADDRESS": "Shop no 6, 7, 8, 9 & Flat No 1, 2 & 3, Omkar Bldg; Village Sathivali Waliv, Vasai (E), Dist. Thane",
        "BANK": "Vasai Vikas Sahakari Bank",
        "BANKCODE": "VVSB",
        "BRANCH": "SATIVALI-WALIV",
        "CENTRE": "SATIVALI",
        "CITY": "SATIVALI",
        "CONTACT": "",
        "DISTRICT": "THANE",
        "IFSC": "VVSB0000014",
        "IMPS": true,
        "MICR": "400803013",
        "NEFT": true,
        "RTGS": true,
        "STATE": "MAHARASHTRA",
        "SWIFT": "",
        "UPI": true
    },
    {
        "ADDRESS": "Shop No. 5, 6, 7, 13, 14 & 15 Gracy ARC CHS, 60 Feet Road, Bhayander (W), Dist. Thane 401101",
        "BANK": "Vasai Vikas Sahakari Bank",
        "BANKCODE": "VVSB",
        "BRANCH": "BHAYANDER (W)",
        "CENTRE": "MIRA-BHAYANDAR",
        "CITY": "MIRA-BHAYANDAR",
        "CONTACT": "28141020",
        "DISTRICT": "THANE",
        "IFSC": "VVSB0000015",
        "IMPS": true,
        "MICR": "400803014",
        "NEFT": true,
        "RTGS": true,
        "STATE": "MAHARASHTRA",
        "SWIFT": "",
        "UPI": true
    },
    {
        "ADDRESS": "Shop No.6 & 7, Martin Plaza, Barampur, Vasai Station Road, Vasai (West), Tal - Vasai, Dist Thane 401202",
        "BANK": "Vasai Vikas Sahakari Bank",
        "BANKCODE": "VVSB",
        "BRANCH": "BARAMPUR",
        "CENTRE": "MANICKPUR",
        "CITY": "MANICKPUR",
        "CONTACT": "2380134",
        "DISTRICT": "THANE",
        "IFSC": "VVSB0000016",
        "IMPS": true,
        "MICR": "400803015",
        "NEFT": true,
        "RTGS": true,
        "STATE": "MAHARASHTRA",
        "SWIFT": "",
        "UPI": true
    },
    {
        "ADDRESS": "M. Baria Lake View, Opp. Hanuman Temple, Bazar Peth, At Post Agashi, Taluka Vasai, Dist. Thane \u2013 401 301",
        "BANK": "Vasai Vikas Sahakari Bank",
        "BANKCODE": "VVSB",
        "BRANCH": "AGASHI",
        "CENTRE": "AGASHI",
        "CITY": "AGASHI",
        "CONTACT": "2584284",
        "DISTRICT": "THANE",
        "IFSC": "VVSB0000017",
        "IMPS": true,
        "MICR": "400803016",
        "NEFT": true,
        "RTGS": true,
        "STATE": "MAHARASHTRA",
        "SWIFT": "",
        "UPI": true
    },
    {
        "ADDRESS": "B-002, Ground Floor, Ornaments Co-operative Housing Society Ltd., Evershine City, Vasai (East) Dist. Thane - 401208",
        "BANK": "Vasai Vikas Sahakari Bank",
        "BANKCODE": "VVSB",
        "BRANCH": "EVERNSHINE",
        "CENTRE": "GOKHIVERA",
        "CITY": "GOKHIVERA",
        "CONTACT": "2460173",
        "DISTRICT": "THANE",
        "IFSC": "VVSB0000018",
        "IMPS": true,
        "MICR": "400803017",
        "NEFT": true,
        "RTGS": true,
        "STATE": "MAHARASHTRA",
        "SWIFT": "",
        "UPI": true
    },
    {
        "ADDRESS": "SHOP NO 8 A/8 ARCHIT REGENCY CO OP HSG. SOCIETY, SAVARKAR NAGAR, GANGAPUR ROAD NASIK",
        "BANK": "Vasai Vikas Sahakari Bank",
        "BANKCODE": "VVSB",
        "BRANCH": "GANGAPUR ROAD",
        "CENTRE": "NASIK",
        "CITY": "NASIK",
        "CONTACT": "02537350015163",
        "DISTRICT": "NASIK",
        "IFSC": "VVSB0000019",
        "IMPS": true,
        "MICR": "422803001",
        "NEFT": true,
        "RTGS": true,
        "STATE": "MAHARASHTRA",
        "SWIFT": "",
        "UPI": true
    },
    {
        "ADDRESS": "ANJALI COMPLEX, PLOT NO 5-6/55/P, CITY SURVEY NO 2963, MILL CORNER, KHADKESHWAR, AURANGABAD",
        "BANK": "Vasai Vikas Sahakari Bank",
        "BANKCODE": "VVSB",
        "BRANCH": "KHADKESHWAR",
        "CENTRE": "AURANGABAD",
        "CITY": "AURANGABAD",
        "CONTACT": "02407735001516",
        "DISTRICT": "AURANGABAD",
        "IFSC": "VVSB0000020",
        "IMPS": true,
        "MICR": "431803002",
        "NEFT": true,
        "RTGS": true,
        "STATE": "MAHARASHTRA",
        "SWIFT": "",
        "UPI": true
    },
    {
        "ADDRESS": "SHOP NO 2,3,4, G/2, VEDSHREE APT. CO-OP HSG SOC LTD. MANVELPADA ROAD VIRAR EAST",
        "BANK": "Vasai Vikas Sahakari Bank",
        "BANKCODE": "VVSB",
        "BRANCH": "MANVELPADA-VIRAR E",
        "CENTRE": "VIRAR",
        "CITY": "VIRAR",
        "CONTACT": "02502326984",
        "DISTRICT": "PALGHAR",
        "IFSC": "VVSB0000021",
        "IMPS": true,
        "MICR": "400803019",
        "NEFT": true,
        "RTGS": true,
        "STATE": "MAHARASHTRA",
        "SWIFT": "",
        "UPI": true
    },
    {
        "ADDRESS": "SHOP NO 7,8,9,10, TULJESHWARI HILL, AMBAWADI, RAMBHAU NAGAR, TULINJ, NALASOPARA EAST",
        "BANK": "Vasai Vikas Sahakari Bank",
        "BANKCODE": "VVSB",
        "BRANCH": "TULINJ-NALASOPARA",
        "CENTRE": "NALASOPARA",
        "CITY": "NALASOPARA",
        "CONTACT": "02502326984",
        "DISTRICT": "PALGHAR",
        "IFSC": "VVSB0000022",
        "IMPS": true,
        "MICR": "400803020",
        "NEFT": true,
        "RTGS": true,
        "STATE": "MAHARASHTRA",
        "SWIFT": "",
        "UPI": true
    }
]